{"2020": {"Derrick Henry": {"Player": "Derrick Henry", "Rush Yds": 2027.0, "Att": 378.0, "TD": 17.0, "20+": 16.0, "40+": 4.0, "Lng": 94.0, "Rush 1st": 98.0, "Rush 1st%": 25.9, "Rush FUM": 3.0}, "Dalvin Cook": {"Player": "Dalvin Cook", "Rush Yds": 1557.0, "Att": 312.0, "TD": 16.0, "20+": 6.0, "40+": 1.0, "Lng": 70.0, "Rush 1st": 91.0, "Rush 1st%": 29.2, "Rush FUM": 4.0}, "Jonathan Taylor": {"Player": "Jonathan Taylor", "Rush Yds": 1169.0, "Att": 232.0, "TD": 11.0, "20+": 7.0, "40+": 3.0, "Lng": 62.0, "Rush 1st": 69.0, "Rush 1st%": 29.7, "Rush FUM": 1.0}, "Aaron Jones": {"Player": "Aaron Jones", "Rush Yds": 1104.0, "Att": 201.0, "TD": 9.0, "20+": 6.0, "40+": 4.0, "Lng": 77.0, "Rush 1st": 52.0, "Rush 1st%": 25.9, "Rush FUM": 1.0}, "David Montgomery": {"Player": "David Montgomery", "Rush Yds": 1070.0, "Att": 247.0, "TD": 8.0, "20+": 5.0, "40+": 2.0, "Lng": 80.0, "Rush 1st": 59.0, "Rush 1st%": 23.9, "Rush FUM": 0.0}, "James Robinson": {"Player": "James Robinson", "Rush Yds": 1070.0, "Att": 240.0, "TD": 7.0, "20+": 5.0, "40+": 1.0, "Lng": 47.0, "Rush 1st": 54.0, "Rush 1st%": 22.5, "Rush FUM": 1.0}, "Nick Chubb": {"Player": "Nick Chubb", "Rush Yds": 1067.0, "Att": 190.0, "TD": 12.0, "20+": 12.0, "40+": 3.0, "Lng": 59.0, "Rush 1st": 55.0, "Rush 1st%": 29.0, "Rush FUM": 1.0}, "Josh Jacobs": {"Player": "Josh Jacobs", "Rush Yds": 1065.0, "Att": 273.0, "TD": 12.0, "20+": 3.0, "40+": 0.0, "Lng": 28.0, "Rush 1st": 61.0, "Rush 1st%": 22.3, "Rush FUM": 2.0}, "Lamar Jackson": {"Player": "Lamar Jackson", "Rush Yds": 1005.0, "Att": 159.0, "TD": 7.0, "20+": 10.0, "40+": 2.0, "Lng": 50.0, "Rush 1st": 56.0, "Rush 1st%": 35.2, "Rush FUM": 5.0}, "Melvin Gordon": {"Player": "Melvin Gordon", "Rush Yds": 986.0, "Att": 215.0, "TD": 9.0, "20+": 5.0, "40+": 2.0, "Lng": 65.0, "Rush 1st": 46.0, "Rush 1st%": 21.4, "Rush FUM": 2.0}, "Ezekiel Elliott": {"Player": "Ezekiel Elliott", "Rush Yds": 979.0, "Att": 244.0, "TD": 6.0, "20+": 3.0, "40+": 0.0, "Lng": 31.0, "Rush 1st": 62.0, "Rush 1st%": 25.4, "Rush FUM": 5.0}, "Ronald Jones": {"Player": "Ronald Jones", "Rush Yds": 978.0, "Att": 192.0, "TD": 7.0, "20+": 6.0, "40+": 1.0, "Lng": 98.0, "Rush 1st": 48.0, "Rush 1st%": 25.0, "Rush FUM": 0.0}, "Kenyan Drake": {"Player": "Kenyan Drake", "Rush Yds": 955.0, "Att": 239.0, "TD": 10.0, "20+": 6.0, "40+": 1.0, "Lng": 69.0, "Rush 1st": 59.0, "Rush 1st%": 24.7, "Rush FUM": 3.0}, "Alvin Kamara": {"Player": "Alvin Kamara", "Rush Yds": 932.0, "Att": 187.0, "TD": 16.0, "20+": 7.0, "40+": 2.0, "Lng": 49.0, "Rush 1st": 58.0, "Rush 1st%": 31.0, "Rush FUM": 1.0}, "Miles Sanders": {"Player": "Miles Sanders", "Rush Yds": 867.0, "Att": 164.0, "TD": 6.0, "20+": 4.0, "40+": 3.0, "Lng": 82.0, "Rush 1st": 39.0, "Rush 1st%": 23.8, "Rush FUM": 4.0}, "Kareem Hunt": {"Player": "Kareem Hunt", "Rush Yds": 841.0, "Att": 198.0, "TD": 6.0, "20+": 3.0, "40+": 0.0, "Lng": 33.0, "Rush 1st": 44.0, "Rush 1st%": 22.2, "Rush FUM": 1.0}, "Kyler Murray": {"Player": "Kyler Murray", "Rush Yds": 819.0, "Att": 133.0, "TD": 11.0, "20+": 7.0, "40+": 1.0, "Lng": 48.0, "Rush 1st": 52.0, "Rush 1st%": 39.1, "Rush FUM": 5.0}, "J.K. Dobbins": {"Player": "J.K. Dobbins", "Rush Yds": 805.0, "Att": 134.0, "TD": 9.0, "20+": 8.0, "40+": 2.0, "Lng": 72.0, "Rush 1st": 38.0, "Rush 1st%": 28.4, "Rush FUM": 2.0}, "Clyde Edwards-Helaire": {"Player": "Clyde Edwards-Helaire", "Rush Yds": 803.0, "Att": 181.0, "TD": 4.0, "20+": 3.0, "40+": 0.0, "Lng": 31.0, "Rush 1st": 39.0, "Rush 1st%": 21.6, "Rush FUM": 0.0}, "Antonio Gibson": {"Player": "Antonio Gibson", "Rush Yds": 795.0, "Att": 170.0, "TD": 11.0, "20+": 5.0, "40+": 1.0, "Lng": 40.0, "Rush 1st": 40.0, "Rush 1st%": 23.5, "Rush FUM": 0.0}, "Gus Edwards": {"Player": "Gus Edwards", "Rush Yds": 723.0, "Att": 144.0, "TD": 6.0, "20+": 8.0, "40+": 0.0, "Lng": 36.0, "Rush 1st": 45.0, "Rush 1st%": 31.2, "Rush FUM": 1.0}, "James Conner": {"Player": "James Conner", "Rush Yds": 721.0, "Att": 169.0, "TD": 6.0, "20+": 5.0, "40+": 1.0, "Lng": 59.0, "Rush 1st": 42.0, "Rush 1st%": 24.8, "Rush FUM": 2.0}, "Damien Harris": {"Player": "Damien Harris", "Rush Yds": 691.0, "Att": 137.0, "TD": 2.0, "20+": 4.0, "40+": 1.0, "Lng": 41.0, "Rush 1st": 30.0, "Rush 1st%": 21.9, "Rush FUM": 1.0}, "David Johnson": {"Player": "David Johnson", "Rush Yds": 691.0, "Att": 147.0, "TD": 6.0, "20+": 4.0, "40+": 1.0, "Lng": 48.0, "Rush 1st": 38.0, "Rush 1st%": 25.8, "Rush FUM": 0.0}, "Devin Singletary": {"Player": "Devin Singletary", "Rush Yds": 687.0, "Att": 156.0, "TD": 2.0, "20+": 3.0, "40+": 1.0, "Lng": 51.0, "Rush 1st": 40.0, "Rush 1st%": 25.6, "Rush FUM": 1.0}}, "2021": {"Jonathan Taylor": {"Player": "Jonathan Taylor", "Rush Yds": 1811.0, "Att": 332.0, "TD": 18.0, "20+": 14.0, "40+": 5.0, "Lng": 83.0, "Rush 1st": 107.0, "Rush 1st%": 32.2, "Rush FUM": 3.0}, "Nick Chubb": {"Player": "Nick Chubb", "Rush Yds": 1259.0, "Att": 228.0, "TD": 8.0, "20+": 12.0, "40+": 2.0, "Lng": 70.0, "Rush 1st": 61.0, "Rush 1st%": 26.8, "Rush FUM": 2.0}, "Joe Mixon": {"Player": "Joe Mixon", "Rush Yds": 1205.0, "Att": 292.0, "TD": 13.0, "20+": 6.0, "40+": 0.0, "Lng": 32.0, "Rush 1st": 60.0, "Rush 1st%": 20.6, "Rush FUM": 1.0}, "Najee Harris": {"Player": "Najee Harris", "Rush Yds": 1200.0, "Att": 307.0, "TD": 7.0, "20+": 6.0, "40+": 0.0, "Lng": 37.0, "Rush 1st": 62.0, "Rush 1st%": 20.2, "Rush FUM": 0.0}, "Dalvin Cook": {"Player": "Dalvin Cook", "Rush Yds": 1159.0, "Att": 249.0, "TD": 6.0, "20+": 9.0, "40+": 1.0, "Lng": 66.0, "Rush 1st": 57.0, "Rush 1st%": 22.9, "Rush FUM": 3.0}, "Antonio Gibson": {"Player": "Antonio Gibson", "Rush Yds": 1037.0, "Att": 258.0, "TD": 7.0, "20+": 4.0, "40+": 0.0, "Lng": 27.0, "Rush 1st": 65.0, "Rush 1st%": 25.2, "Rush FUM": 5.0}, "Ezekiel Elliott": {"Player": "Ezekiel Elliott", "Rush Yds": 1002.0, "Att": 237.0, "TD": 10.0, "20+": 3.0, "40+": 1.0, "Lng": 47.0, "Rush 1st": 55.0, "Rush 1st%": 23.2, "Rush FUM": 1.0}, "Elijah Mitchell": {"Player": "Elijah Mitchell", "Rush Yds": 963.0, "Att": 207.0, "TD": 5.0, "20+": 6.0, "40+": 0.0, "Lng": 39.0, "Rush 1st": 47.0, "Rush 1st%": 22.7, "Rush FUM": 0.0}, "Derrick Henry": {"Player": "Derrick Henry", "Rush Yds": 937.0, "Att": 219.0, "TD": 10.0, "20+": 3.0, "40+": 2.0, "Lng": 76.0, "Rush 1st": 49.0, "Rush 1st%": 22.4, "Rush FUM": 1.0}, "Damien Harris": {"Player": "Damien Harris", "Rush Yds": 929.0, "Att": 202.0, "TD": 15.0, "20+": 8.0, "40+": 1.0, "Lng": 64.0, "Rush 1st": 55.0, "Rush 1st%": 27.2, "Rush FUM": 2.0}, "Melvin Gordon": {"Player": "Melvin Gordon", "Rush Yds": 918.0, "Att": 203.0, "TD": 8.0, "20+": 3.0, "40+": 2.0, "Lng": 70.0, "Rush 1st": 48.0, "Rush 1st%": 23.6, "Rush FUM": 3.0}, "Austin Ekeler": {"Player": "Austin Ekeler", "Rush Yds": 911.0, "Att": 206.0, "TD": 12.0, "20+": 3.0, "40+": 0.0, "Lng": 28.0, "Rush 1st": 53.0, "Rush 1st%": 25.7, "Rush FUM": 0.0}, "Javonte Williams": {"Player": "Javonte Williams", "Rush Yds": 903.0, "Att": 203.0, "TD": 4.0, "20+": 6.0, "40+": 1.0, "Lng": 49.0, "Rush 1st": 52.0, "Rush 1st%": 25.6, "Rush FUM": 2.0}, "Alvin Kamara": {"Player": "Alvin Kamara", "Rush Yds": 898.0, "Att": 240.0, "TD": 4.0, "20+": 3.0, "40+": 0.0, "Lng": 30.0, "Rush 1st": 42.0, "Rush 1st%": 17.5, "Rush FUM": 0.0}, "Josh Jacobs": {"Player": "Josh Jacobs", "Rush Yds": 872.0, "Att": 217.0, "TD": 9.0, "20+": 2.0, "40+": 0.0, "Lng": 28.0, "Rush 1st": 45.0, "Rush 1st%": 20.7, "Rush FUM": 2.0}, "Devin Singletary": {"Player": "Devin Singletary", "Rush Yds": 870.0, "Att": 188.0, "TD": 7.0, "20+": 6.0, "40+": 2.0, "Lng": 46.0, "Rush 1st": 44.0, "Rush 1st%": 23.4, "Rush FUM": 2.0}, "David Montgomery": {"Player": "David Montgomery", "Rush Yds": 846.0, "Att": 225.0, "TD": 7.0, "20+": 5.0, "40+": 1.0, "Lng": 41.0, "Rush 1st": 55.0, "Rush 1st%": 24.4, "Rush FUM": 2.0}, "Sony Michel": {"Player": "Sony Michel", "Rush Yds": 845.0, "Att": 208.0, "TD": 4.0, "20+": 2.0, "40+": 0.0, "Lng": 39.0, "Rush 1st": 49.0, "Rush 1st%": 23.6, "Rush FUM": 1.0}, "Leonard Fournette": {"Player": "Leonard Fournette", "Rush Yds": 812.0, "Att": 180.0, "TD": 8.0, "20+": 5.0, "40+": 1.0, "Lng": 47.0, "Rush 1st": 45.0, "Rush 1st%": 25.0, "Rush FUM": 0.0}, "AJ Dillon": {"Player": "AJ Dillon", "Rush Yds": 803.0, "Att": 187.0, "TD": 5.0, "20+": 2.0, "40+": 0.0, "Lng": 36.0, "Rush 1st": 50.0, "Rush 1st%": 26.7, "Rush FUM": 1.0}, "Aaron Jones": {"Player": "Aaron Jones", "Rush Yds": 799.0, "Att": 171.0, "TD": 4.0, "20+": 5.0, "40+": 1.0, "Lng": 57.0, "Rush 1st": 37.0, "Rush 1st%": 21.6, "Rush FUM": 1.0}, "Jalen Hurts": {"Player": "Jalen Hurts", "Rush Yds": 784.0, "Att": 139.0, "TD": 10.0, "20+": 7.0, "40+": 0.0, "Lng": 31.0, "Rush 1st": 56.0, "Rush 1st%": 40.3, "Rush FUM": 4.0}, "Lamar Jackson": {"Player": "Lamar Jackson", "Rush Yds": 767.0, "Att": 133.0, "TD": 2.0, "20+": 5.0, "40+": 0.0, "Lng": 31.0, "Rush 1st": 48.0, "Rush 1st%": 36.1, "Rush FUM": 3.0}, "James Robinson": {"Player": "James Robinson", "Rush Yds": 767.0, "Att": 164.0, "TD": 8.0, "20+": 4.0, "40+": 1.0, "Lng": 58.0, "Rush 1st": 41.0, "Rush 1st%": 25.0, "Rush FUM": 2.0}, "Josh Allen": {"Player": "Josh Allen", "Rush Yds": 763.0, "Att": 122.0, "TD": 6.0, "20+": 9.0, "40+": 0.0, "Lng": 34.0, "Rush 1st": 54.0, "Rush 1st%": 44.3, "Rush FUM": 5.0}}, "2022": {"Josh Jacobs": {"Player": "Josh Jacobs", "Rush Yds": 1653.0, "Att": 340.0, "TD": 12.0, "20+": 7.0, "40+": 2.0, "Lng": 86.0, "Rush 1st": 93.0, "Rush 1st%": 27.4, "Rush FUM": 2.0}, "Derrick Henry": {"Player": "Derrick Henry", "Rush Yds": 1538.0, "Att": 349.0, "TD": 13.0, "20+": 10.0, "40+": 4.0, "Lng": 56.0, "Rush 1st": 65.0, "Rush 1st%": 18.6, "Rush FUM": 4.0}, "Nick Chubb": {"Player": "Nick Chubb", "Rush Yds": 1525.0, "Att": 302.0, "TD": 12.0, "20+": 13.0, "40+": 1.0, "Lng": 41.0, "Rush 1st": 69.0, "Rush 1st%": 22.8, "Rush FUM": 1.0}, "Saquon Barkley": {"Player": "Saquon Barkley", "Rush Yds": 1312.0, "Att": 295.0, "TD": 10.0, "20+": 9.0, "40+": 2.0, "Lng": 68.0, "Rush 1st": 62.0, "Rush 1st%": 21.0, "Rush FUM": 1.0}, "Miles Sanders": {"Player": "Miles Sanders", "Rush Yds": 1269.0, "Att": 259.0, "TD": 11.0, "20+": 9.0, "40+": 1.0, "Lng": 40.0, "Rush 1st": 62.0, "Rush 1st%": 23.9, "Rush FUM": 1.0}, "Dalvin Cook": {"Player": "Dalvin Cook", "Rush Yds": 1173.0, "Att": 264.0, "TD": 8.0, "20+": 5.0, "40+": 3.0, "Lng": 81.0, "Rush 1st": 50.0, "Rush 1st%": 18.9, "Rush FUM": 3.0}, "Justin Fields": {"Player": "Justin Fields", "Rush Yds": 1143.0, "Att": 160.0, "TD": 8.0, "20+": 10.0, "40+": 4.0, "Lng": 67.0, "Rush 1st": 65.0, "Rush 1st%": 40.6, "Rush FUM": 8.0}, "Christian McCaffrey": {"Player": "Christian McCaffrey", "Rush Yds": 1139.0, "Att": 244.0, "TD": 8.0, "20+": 9.0, "40+": 1.0, "Lng": 49.0, "Rush 1st": 59.0, "Rush 1st%": 24.2, "Rush FUM": 1.0}, "Travis Etienne": {"Player": "Travis Etienne", "Rush Yds": 1125.0, "Att": 220.0, "TD": 5.0, "20+": 8.0, "40+": 4.0, "Lng": 62.0, "Rush 1st": 52.0, "Rush 1st%": 23.6, "Rush FUM": 3.0}, "Aaron Jones": {"Player": "Aaron Jones", "Rush Yds": 1121.0, "Att": 213.0, "TD": 2.0, "20+": 6.0, "40+": 0.0, "Lng": 36.0, "Rush 1st": 54.0, "Rush 1st%": 25.4, "Rush FUM": 3.0}, "Jamaal Williams": {"Player": "Jamaal Williams", "Rush Yds": 1066.0, "Att": 262.0, "TD": 17.0, "20+": 4.0, "40+": 2.0, "Lng": 58.0, "Rush 1st": 65.0, "Rush 1st%": 24.8, "Rush FUM": 3.0}, "Kenneth Walker III": {"Player": "Kenneth Walker III", "Rush Yds": 1050.0, "Att": 228.0, "TD": 9.0, "20+": 10.0, "40+": 3.0, "Lng": 74.0, "Rush 1st": 51.0, "Rush 1st%": 22.4, "Rush FUM": 0.0}, "Rhamondre Stevenson": {"Player": "Rhamondre Stevenson", "Rush Yds": 1040.0, "Att": 210.0, "TD": 5.0, "20+": 7.0, "40+": 1.0, "Lng": 49.0, "Rush 1st": 49.0, "Rush 1st%": 23.3, "Rush FUM": 2.0}, "Tyler Allgeier": {"Player": "Tyler Allgeier", "Rush Yds": 1035.0, "Att": 210.0, "TD": 3.0, "20+": 6.0, "40+": 3.0, "Lng": 44.0, "Rush 1st": 53.0, "Rush 1st%": 25.2, "Rush FUM": 0.0}, "Najee Harris": {"Player": "Najee Harris", "Rush Yds": 1034.0, "Att": 272.0, "TD": 7.0, "20+": 1.0, "40+": 0.0, "Lng": 36.0, "Rush 1st": 45.0, "Rush 1st%": 16.5, "Rush FUM": 2.0}, "Tony Pollard": {"Player": "Tony Pollard", "Rush Yds": 1007.0, "Att": 193.0, "TD": 9.0, "20+": 9.0, "40+": 3.0, "Lng": 57.0, "Rush 1st": 46.0, "Rush 1st%": 23.8, "Rush FUM": 0.0}, "Dameon Pierce": {"Player": "Dameon Pierce", "Rush Yds": 939.0, "Att": 220.0, "TD": 4.0, "20+": 7.0, "40+": 2.0, "Lng": 75.0, "Rush 1st": 54.0, "Rush 1st%": 24.6, "Rush FUM": 4.0}, "Austin Ekeler": {"Player": "Austin Ekeler", "Rush Yds": 915.0, "Att": 204.0, "TD": 13.0, "20+": 4.0, "40+": 2.0, "Lng": 72.0, "Rush 1st": 46.0, "Rush 1st%": 22.6, "Rush FUM": 3.0}, "D'Onta Foreman": {"Player": "D'Onta Foreman", "Rush Yds": 914.0, "Att": 203.0, "TD": 5.0, "20+": 8.0, "40+": 1.0, "Lng": 60.0, "Rush 1st": 45.0, "Rush 1st%": 22.2, "Rush FUM": 1.0}, "Alvin Kamara": {"Player": "Alvin Kamara", "Rush Yds": 897.0, "Att": 223.0, "TD": 2.0, "20+": 3.0, "40+": 0.0, "Lng": 27.0, "Rush 1st": 40.0, "Rush 1st%": 17.9, "Rush FUM": 2.0}, "Raheem Mostert": {"Player": "Raheem Mostert", "Rush Yds": 891.0, "Att": 181.0, "TD": 3.0, "20+": 6.0, "40+": 1.0, "Lng": 67.0, "Rush 1st": 44.0, "Rush 1st%": 24.3, "Rush FUM": 1.0}, "Ezekiel Elliott": {"Player": "Ezekiel Elliott", "Rush Yds": 876.0, "Att": 231.0, "TD": 12.0, "20+": 5.0, "40+": 0.0, "Lng": 27.0, "Rush 1st": 52.0, "Rush 1st%": 22.5, "Rush FUM": 0.0}, "Jonathan Taylor": {"Player": "Jonathan Taylor", "Rush Yds": 861.0, "Att": 192.0, "TD": 4.0, "20+": 5.0, "40+": 1.0, "Lng": 66.0, "Rush 1st": 39.0, "Rush 1st%": 20.3, "Rush FUM": 3.0}, "Jeff Wilson": {"Player": "Jeff Wilson", "Rush Yds": 860.0, "Att": 176.0, "TD": 5.0, "20+": 7.0, "40+": 1.0, "Lng": 41.0, "Rush 1st": 43.0, "Rush 1st%": 24.4, "Rush FUM": 2.0}, "Isiah Pacheco": {"Player": "Isiah Pacheco", "Rush Yds": 830.0, "Att": 170.0, "TD": 5.0, "20+": 3.0, "40+": 0.0, "Lng": 31.0, "Rush 1st": 37.0, "Rush 1st%": 21.8, "Rush FUM": 3.0}}}